thisnotthat/__init__.py
thisnotthat/_version.py
thisnotthat/bokeh_plot.py
thisnotthat/data_viewer.py
thisnotthat/deckgl_plot.py
thisnotthat/image_utils.py
thisnotthat/instance_viewer.py
thisnotthat/label_editor.py
thisnotthat/map_cluster_labelling.py
thisnotthat/palettes.py
thisnotthat/plot_controls.py
thisnotthat/search.py
thisnotthat/selector.py
thisnotthat/utils.py
thisnotthat/summary/__init__.py
thisnotthat/summary/dataframe.py
thisnotthat/summary/plot.py
thisnotthat/tests/__init__.py
thisnotthat/tests/conftest.py
thisnotthat/tests/test_cluster_labelling.py
thisnotthat/tests/ui/__init__.py
thisnotthat/tests/ui/test_datapane.py
thisnotthat-0.4.2.dist-info/LICENSE
thisnotthat-0.4.2.dist-info/METADATA
thisnotthat-0.4.2.dist-info/WHEEL
thisnotthat-0.4.2.dist-info/top_level.txt
thisnotthat-0.4.2.dist-info/RECORD
