Metadata-Version: 2.1
Name: thisnotthat
Version: 0.4.2
Summary: Tools for interactive visualization and exploration of _data maps_
Home-page: https://github.com/TutteInstitute/thisnotthat
Download-URL: https://github.com/TutteInstitute/thisnotthat
Maintainer: Benoit Hamelin, John Healy, Leland McInnes
Maintainer-email: leland.mcinnes@gmail.com
License: new BSD
Classifier: Intended Audience :: Science/Research
Classifier: Intended Audience :: Developers
Classifier: License :: OSI Approved
Classifier: Programming Language :: Python
Classifier: Topic :: Software Development
Classifier: Topic :: Scientific/Engineering
Classifier: Operating System :: Microsoft :: Windows
Classifier: Operating System :: POSIX
Classifier: Operating System :: Unix
Classifier: Operating System :: MacOS
Classifier: Programming Language :: Python :: 3.9
Classifier: Programming Language :: Python :: 3.10
License-File: LICENSE
Requires-Dist: bokeh
Requires-Dist: cmocean
Requires-Dist: colorcet
Requires-Dist: glasbey
Requires-Dist: hdbscan
Requires-Dist: matplotlib
Requires-Dist: numpy>=1.22
Requires-Dist: pandas
Requires-Dist: panel
Requires-Dist: param
Requires-Dist: scikit-learn>=1.2.0
Requires-Dist: umap-learn
Requires-Dist: vectorizers
Requires-Dist: wordcloud
Provides-Extra: docs
Requires-Dist: sphinx; extra == "docs"
Requires-Dist: sphinx-gallery; extra == "docs"
Requires-Dist: nbsphinx; extra == "docs"
Requires-Dist: sphinx-rtd-theme; extra == "docs"
Requires-Dist: numpydoc; extra == "docs"
Requires-Dist: matplotlib; extra == "docs"
Provides-Extra: tests
Requires-Dist: pytest; extra == "tests"
Requires-Dist: pytest-cov; extra == "tests"
Requires-Dist: psutil; extra == "tests"
Requires-Dist: pytest-asyncio; extra == "tests"
Requires-Dist: pytest-rerunfailures; extra == "tests"
Requires-Dist: pytest-xdist; extra == "tests"
Requires-Dist: pytest-playwright; extra == "tests"
